mlforce/__init__.py
mlforce/basics/__init__.py
mlforce/basics/algorithms.py
mlforce/basics/datasets.py
mlforce/mf/__init__.py
mlforce/mf/nmf.py
mlforce/nn/__init__.py
mlforce/nn/callbacks.py
mlforce/nn/functional.py
mlforce/nn/layers.py
mlforce/nn/mlp.py
mlforce/nn/optim.py
mlforce/nn/schedules.py
mlforce-1.0.0.dist-info/LICENSE
mlforce-1.0.0.dist-info/METADATA
mlforce-1.0.0.dist-info/WHEEL
mlforce-1.0.0.dist-info/top_level.txt
mlforce-1.0.0.dist-info/RECORD
