Metadata-Version: 2.1
Name: mlforce
Version: 1.0.0
Summary: Easy-to-use machine learning toolkit for beginners
Home-page: https://github.com/XavierSpycy/MLForce
Author: Jiarui Xu
Author-email: xujiarui98@foxmail.com
Classifier: Programming Language :: Python :: 3
Classifier: License :: OSI Approved :: MIT License
Classifier: Operating System :: OS Independent
Requires-Python: >=3.6
License-File: LICENSE
Requires-Dist: numpy
Requires-Dist: pandas
Requires-Dist: scipy
